tonconnect/__init__.py
tonconnect/apps.py
tonconnect/bridge.py
tonconnect/connector.py
tonconnect/crypto.py
tonconnect/events.py
tonconnect/exceptions.py
tonconnect/httpbridge.py
tonconnect/metadata.py
tonconnect/options.py
tonconnect/requests.py
tonconnect/url.py
tonconnect/utils.py
tonconnect/wallet.py
tonconnect-0.2.0.dist-info/LICENSE.md
tonconnect-0.2.0.dist-info/WHEEL
tonconnect-0.2.0.dist-info/METADATA
tonconnect-0.2.0.dist-info/RECORD
