Metadata-Version: 2.1
Name: tonconnect
Version: 0.2.0
Summary: TON Connect - Python library for using TON Connect 2.
Author: Vlad100
Requires-Dist: pynacl
Requires-Dist: requests
Requires-Dist: tonsdk
Requires-Dist: aiohttp
Project-URL: Documentation, https://github.com/ClickoTON-Foundation/tonconnect
Project-URL: Homepage, https://github.com/ClickoTON-Foundation/tonconnect
Project-URL: Repository, https://github.com/ClickoTON-Foundation/tonconnect/
